slidedeckai/__init__.py
slidedeckai/_version.py
slidedeckai/cli.py
slidedeckai/core.py
slidedeckai/global_config.py
slidedeckai/strings.json
slidedeckai/file_embeddings/embeddings.npy
slidedeckai/file_embeddings/icons.npy
slidedeckai/helpers/__init__.py
slidedeckai/helpers/chat_helper.py
slidedeckai/helpers/file_manager.py
slidedeckai/helpers/icons_embeddings.py
slidedeckai/helpers/image_search.py
slidedeckai/helpers/llm_helper.py
slidedeckai/helpers/pptx_helper.py
slidedeckai/helpers/text_helper.py
slidedeckai/icons/svg_repo.txt
slidedeckai/icons/png128/0-circle.png
slidedeckai/icons/png128/1-circle.png
slidedeckai/icons/png128/123.png
slidedeckai/icons/png128/2-circle.png
slidedeckai/icons/png128/3-circle.png
slidedeckai/icons/png128/4-circle.png
slidedeckai/icons/png128/5-circle.png
slidedeckai/icons/png128/6-circle.png
slidedeckai/icons/png128/7-circle.png
slidedeckai/icons/png128/8-circle.png
slidedeckai/icons/png128/9-circle.png
slidedeckai/icons/png128/activity.png
slidedeckai/icons/png128/airplane.png
slidedeckai/icons/png128/alarm.png
slidedeckai/icons/png128/alien-head.png
slidedeckai/icons/png128/alphabet.png
slidedeckai/icons/png128/amazon.png
slidedeckai/icons/png128/amritsar-golden-temple.png
slidedeckai/icons/png128/amsterdam-canal.png
slidedeckai/icons/png128/amsterdam-windmill.png
slidedeckai/icons/png128/android.png
slidedeckai/icons/png128/angkor-wat.png
slidedeckai/icons/png128/apple.png
slidedeckai/icons/png128/archive.png
slidedeckai/icons/png128/argentina-obelisk.png
slidedeckai/icons/png128/artificial-intelligence-brain.png
slidedeckai/icons/png128/atlanta.png
slidedeckai/icons/png128/austin.png
slidedeckai/icons/png128/automation-decision.png
slidedeckai/icons/png128/award.png
slidedeckai/icons/png128/balloon.png
slidedeckai/icons/png128/ban.png
slidedeckai/icons/png128/bandaid.png
slidedeckai/icons/png128/bangalore.png
slidedeckai/icons/png128/bank.png
slidedeckai/icons/png128/bar-chart-line.png
slidedeckai/icons/png128/barcelona.png
slidedeckai-8.0.7.dist-info/licenses/LICENSE
slidedeckai-8.0.7.dist-info/METADATA
slidedeckai-8.0.7.dist-info/WHEEL
slidedeckai-8.0.7.dist-info/entry_points.txt
slidedeckai-8.0.7.dist-info/top_level.txt
slidedeckai-8.0.7.dist-info/RECORD
