Metadata-Version: 2.4
Name: slidedeckai
Version: 8.0.7
Summary: Co-create PowerPoint slide decks with AI
Author-email: Barun Saha <author@example.com>
Project-URL: Homepage, https://github.com/barun-saha/slide-deck-ai
Project-URL: Bug Tracker, https://github.com/barun-saha/slide-deck-ai/issues
Classifier: Programming Language :: Python :: 3
Classifier: License :: OSI Approved :: MIT License
Classifier: Operating System :: OS Independent
Requires-Python: >=3.10
License-File: LICENSE
Requires-Dist: aiohttp>=3.13.3
Requires-Dist: python-dotenv[cli]~=1.2.1
Requires-Dist: gitpython==3.1.46
Requires-Dist: json-repair~=0.55.1
Requires-Dist: idna==3.11
Requires-Dist: jinja2>=3.1.6
Requires-Dist: Pillow~=12.1.0
Requires-Dist: pyarrow~=22.0.0
Requires-Dist: pydantic~=2.12.5
Requires-Dist: litellm~=1.81.5
Requires-Dist: google-genai
Requires-Dist: streamlit==1.53.1
Requires-Dist: protobuf~=6.33.5
Requires-Dist: python-pptx~=1.0.2
Requires-Dist: json5~=0.12.1
Requires-Dist: requests~=2.32.5
Requires-Dist: pypdf~=6.6.2
Requires-Dist: transformers>=4.52.1
Requires-Dist: torch~=2.9.1
Requires-Dist: lxml~=6.0.2
Requires-Dist: tqdm~=4.66.5
Requires-Dist: numpy
Requires-Dist: scikit-learn~=1.5.1
Requires-Dist: certifi==2024.8.30
Requires-Dist: urllib3>=2.6.3
Requires-Dist: anyio~=4.12.1
Requires-Dist: httpx~=0.28.1
Requires-Dist: huggingface-hub
Requires-Dist: ollama~=0.6.1
Dynamic: license-file
